pylitetouch/__init__.py
pylitetouch/pylitetouch.py
pylitetouch/test_ltmodule.py
pylitetouch-0.1.8.dist-info/LICENSE
pylitetouch-0.1.8.dist-info/METADATA
pylitetouch-0.1.8.dist-info/WHEEL
pylitetouch-0.1.8.dist-info/top_level.txt
pylitetouch-0.1.8.dist-info/RECORD
