Metadata-Version: 2.1
Name: pylitetouch
Version: 0.1.8
Summary: LiteTouch 5000LC
Home-page: https://github.com/patmann03/pylitetouch
Author: Patrick Carr
Author-email: patrick.carr03@gmail.com
License: UNKNOWN
Platform: UNKNOWN
Classifier: Programming Language :: Python :: 3
Classifier: License :: OSI Approved :: GNU General Public License v3 or later (GPLv3+)
Classifier: Operating System :: OS Independent
Requires-Python: >=3.6
